django_nctu_oauth-0.1.0.dist-info/DESCRIPTION.rst
django_nctu_oauth-0.1.0.dist-info/LICENSE.txt
django_nctu_oauth-0.1.0.dist-info/METADATA
django_nctu_oauth-0.1.0.dist-info/RECORD
django_nctu_oauth-0.1.0.dist-info/WHEEL
django_nctu_oauth-0.1.0.dist-info/metadata.json
django_nctu_oauth-0.1.0.dist-info/top_level.txt
nctu_oauth/__init__.py
nctu_oauth/oauth.py
nctu_oauth/urls.py
nctu_oauth/views.py
test/__init__.py
test/settings.py
test/test.py
test/test_data.py
