Metadata-Version: 2.0
Name: django-nctu-oauth
Version: 0.1.0
Summary: NCTU OAuth package for django
Home-page: https://github.com/theblackcat102/django-nctu-oauth
Author: theblackcat
Author-email: zhirui09400@gmail.com
License: UNKNOWN
Keywords: django nctu oauth
Platform: UNKNOWN
Classifier: Development Status :: 3 - Alpha
Classifier: Intended Audience :: Developers
Classifier: Topic :: Software Development :: Build Tools
Classifier: License :: OSI Approved :: MIT License
Classifier: Programming Language :: Python :: 2
Classifier: Programming Language :: Python :: 2.7
Classifier: Programming Language :: Python :: 3
Classifier: Programming Language :: Python :: 3.4
Classifier: Programming Language :: Python :: 3.5
Classifier: Programming Language :: Python :: 3.6
Requires-Dist: ndg-httpsclient
Requires-Dist: pyOpenSSL
Requires-Dist: requests
Provides-Extra: dev
Requires-Dist: check-manifest; extra == 'dev'
Provides-Extra: test
Requires-Dist: coverage; extra == 'test'
